MANIFEST.in
README.rst
setup.py
sanepg/__init__.py
sanepg/connection.py
sanepg/pool.py
sanepg/version.py
sanepg.egg-info/PKG-INFO
sanepg.egg-info/SOURCES.txt
sanepg.egg-info/dependency_links.txt
sanepg.egg-info/requires.txt
sanepg.egg-info/top_level.txt
test/test-server.py